receipt_lib/__init__.py
receipt_lib/formatter.py
receipt_lib-0.1.1.dist-info/licenses/LICENSE
receipt_lib-0.1.1.dist-info/METADATA
receipt_lib-0.1.1.dist-info/WHEEL
receipt_lib-0.1.1.dist-info/top_level.txt
receipt_lib-0.1.1.dist-info/RECORD
