Metadata-Version: 2.4
Name: receipt_lib
Version: 0.1.1
Summary: This is a python package for generating date of transaction and transaction code.
Home-page: 
Author: Bhargavi Gadhepally
Author-email: x23344440@student.ncirl.ie
Keywords: receipt_lib
Classifier: Intended Audience :: Education
Classifier: Operating System :: Microsoft :: Windows :: Windows 10
Classifier: License :: OSI Approved :: MIT License
Classifier: Programming Language :: Python :: 3
Requires-Python: >=3.6
License-File: LICENSE
Dynamic: author
Dynamic: author-email
Dynamic: classifier
Dynamic: description
Dynamic: keywords
Dynamic: license-file
Dynamic: requires-python
Dynamic: summary
